convert2pyc/__init__.py
convert2pyc-0.1.dist-info/METADATA
convert2pyc-0.1.dist-info/WHEEL
convert2pyc-0.1.dist-info/entry_points.txt
convert2pyc-0.1.dist-info/top_level.txt
convert2pyc-0.1.dist-info/RECORD
