Metadata-Version: 2.1
Name: convert2pyc
Version: 0.1
Summary: convert py to pyc
Home-page: UNKNOWN
Author: zxg
Author-email: 
License: UNKNOWN
Platform: UNKNOWN
